fastapi_simple_auth_basic/__init__.py
fastapi_simple_auth_basic/statics/css/styles.css
fastapi_simple_auth_basic/statics/images/github-mark.svg
fastapi_simple_auth_basic/statics/js/simpleauth.js
fastapi_simple_auth_basic/templates/afterlogin.html
fastapi_simple_auth_basic/templates/base.html
fastapi_simple_auth_basic/templates/login.html
fastapi_simple_auth_basic/templates/profile.html
fastapi_simple_auth_basic/templates/recover.html
fastapi_simple_auth_basic/templates/recover_code.html
fastapi_simple_auth_basic/templates/register.html
fastapi_simple_auth_basic/templates/verify-email.html
fastapi_simple_auth_basic/templates/email/change-email.html
fastapi_simple_auth_basic/templates/email/confirm-email.html
fastapi_simple_auth_basic/templates/email/recover.html
fastapi_simple_auth_basic-0.0.6.dist-info/METADATA
fastapi_simple_auth_basic-0.0.6.dist-info/WHEEL
fastapi_simple_auth_basic-0.0.6.dist-info/licenses/LICENSE
fastapi_simple_auth_basic-0.0.6.dist-info/RECORD
